gsearch/__init__.py
gsearch/__init__.pyc
gsearch/data.py
gsearch/data.pyc
gsearch/googlesearch.py
gsearch/googlesearch.pyc
gsearch-1.6.0.dist-info/DESCRIPTION.rst
gsearch-1.6.0.dist-info/METADATA
gsearch-1.6.0.dist-info/RECORD
gsearch-1.6.0.dist-info/WHEEL
gsearch-1.6.0.dist-info/entry_points.txt
gsearch-1.6.0.dist-info/metadata.json
gsearch-1.6.0.dist-info/top_level.txt
