Metadata-Version: 1.1
Name: gsearch
Version: 1.6.0
Summary: Google Search unofficial API for Python with no external dependencies
Home-page: https://github.com/aviaryan/python-gsearch
Author: Avi Aryan
Author-email: avi.aryan123@gmail.com
License: UNKNOWN
Keywords: search-api google python
Platform: UNKNOWN
Classifier: Development Status :: 5 - Production/Stable
Classifier: Topic :: Utilities
Classifier: License :: OSI Approved :: MIT License
Classifier: Programming Language :: Python :: 3
Classifier: Programming Language :: Python :: 2
